{
  "Bulbasaur": { "Ivysaur": { "type": "level", "value": 16 } },
  "Ivysaur": { "Venusaur": { "type": "level", "value": 32 } },
  "Charmander": { "Charmeleon": { "type": "level", "value": 16 } },
  "Charmeleon": { "Charizard": { "type": "level", "value": 36 } },
  "Squirtle": { "Wartortle": { "type": "level", "value": 16 } },
  "Wartortle": { "Blastoise": { "type": "level", "value": 36 } },
  "Caterpie": { "Metapod": { "type": "level", "value": 7 } },
  "Metapod": { "Butterfree": { "type": "level", "value": 10 } },
  "Weedle": { "Kakuna": { "type": "level", "value": 7 } },
  "Kakuna": { "Beedrill": { "type": "level", "value": 10 } },
  "Pidgey": { "Pidgeotto": { "type": "level", "value": 18 } },
  "Pidgeotto": { "Pidgeot": { "type": "level", "value": 36 } },
  "Rattata": { "Raticate": { "type": "level", "value": 20 } },
  "Spearow": { "Fearow": { "type": "level", "value": 20 } },
  "Ekans": { "Arbok": { "type": "level", "value": 22 } },
  "Pikachu": { "Raichu": { "type": "stone", "value": "Thunder_Stone" } },
  "Sandshrew": { "Sandslash": { "type": "level", "value": 22 } },
  "NidoranF": { "Nidorina": { "type": "level", "value": 16 } },
  "Nidorina": { "Nidoqueen": { "type": "stone", "value": "Moon_Stone" } },
  "NidoranM": { "Nidorino": { "type": "level", "value": 16 } },
  "Nidorino": { "Nidoking": { "type": "stone", "value": "Moon_Stone" } },
  "Clefairy": { "Clefable": { "type": "stone", "value": "Moon_Stone" } },
  "Vulpix": { "Ninetales": { "type": "stone", "value": "Fire_Stone" } },
  "Jigglypuff": { "Wigglytuff": { "type": "stone", "value": "Moon_Stone" } },
  "Zubat": { "Golbat": { "type": "level", "value": 22 } },
  "Oddish": { "Gloom": { "type": "level", "value": 21 } },
  "Gloom": { "Vileplume": { "type": "stone", "value": "Leaf_Stone" } },
  "Paras": { "Parasect": { "type": "level", "value": 24 } },
  "Venonat": { "Venomoth": { "type": "level", "value": 31 } },
  "Diglett": { "Dugtrio": { "type": "level", "value": 26 } },
  "Meowth": { "Persian": { "type": "level", "value": 28 } },
  "Psyduck": { "Golduck": { "type": "level", "value": 33 } },
  "Mankey": { "Primeape": { "type": "level", "value": 28 } },
  "Growlithe": { "Arcanine": { "type": "stone", "value": "Fire_Stone" } },
  "Poliwag": { "Poliwhirl": { "type": "level", "value": 25 } },
  "Poliwhirl": { "Poliwrath": { "type": "stone", "value": "Water_Stone" } },
  "Abra": { "Kadabra": { "type": "level", "value": 16 } },
  "Kadabra": { "Alakazam": { "type": "Trade", "value": "Trade" } },
  "Machop": { "Machoke": { "type": "level", "value": 28 } },
  "Machoke": { "Machamp": { "type": "Trade", "value": "Trade" } },
  "Bellsprout": { "Weepinbell": { "type": "level", "value": 21 } },
  "Weepinbell": { "Victreebel": { "type": "stone", "value": "Leaf_Stone" } },
  "Tentacool": { "Tentacruel": { "type": "level", "value": 30 } },
  "Geodude": { "Graveler": { "type": "level", "value": 25 } },
  "Graveler": { "Golem": { "type": "Trade", "value": "Trade" } },
  "Ponyta": { "Rapidash": { "type": "level", "value": 40 } },
  "Slowpoke": { "Slowbro": { "type": "level", "value": 37 } },
  "Magnemite": { "Magneton": { "type": "level", "value": 30 } },
  "Doduo": { "Dodrio": { "type": "level", "value": 31 } },
  "Seel": { "Dewgong": { "type": "level", "value": 34 } },
  "Grimer": { "Muk": { "type": "level", "value": 38 } },
  "Shellder": { "Cloyster": { "type": "stone", "value": "Water_Stone" } },
  "Gastly": { "Haunter": { "type": "level", "value": 25 } },
  "Haunter": { "Gengar": { "type": "Trade", "value": "Trade" } },
  "Drowzee": { "Hypno": { "type": "level", "value": 26 } },
  "Voltorb": { "Electrode": { "type": "level", "value": 30 } },
  "Exeggcute": { "Exeggutor": { "type": "stone", "value": "Leaf_Stone" } },
  "Cubone": { "Marowak": { "type": "level", "value": 28 } },
  "Koffing": { "Weezing": { "type": "level", "value": 35 } },
  "Rhyhorn": { "Rhydon": { "type": "level", "value": 42 } },
  "Horsea": { "Seadra": { "type": "level", "value": 32 } },
  "Goldeen": { "Seaking": { "type": "level", "value": 33 } },
  "Staryu": { "Starmie": { "type": "stone", "value": "Water_Stone" } },
  "Magikarp": { "Gyarados": { "type": "level", "value": 20 } },
  "Eevee": { "Vaporeon": { "type": "stone", "value": "Water_Stone" },
             "Jolteon":  { "type": "stone", "value": "Thunder_Stone" },
             "Flareon":  { "type": "stone", "value": "Fire_Stone" } },
  "Omanyte": { "Omastar": { "type": "level", "value": 40 } },
  "Kabuto": { "Kabutops": { "type": "level", "value": 40 } },
  "Dratini": { "Dragonair": { "type": "level", "value": 30 } },
  "Dragonair": { "Dragonite": { "type": "level", "value": 55 } }
}
